README.md
setup.cfg
setup.py
daraja_api/__init__.py
daraja_api/auth.py
daraja_api/conf.py
daraja_api/exceptions.py
daraja_api/utils.py
daraja_api.egg-info/PKG-INFO
daraja_api.egg-info/SOURCES.txt
daraja_api.egg-info/dependency_links.txt
daraja_api.egg-info/requires.txt
daraja_api.egg-info/top_level.txt
daraja_api/clients/__init__.py
daraja_api/clients/abstract_api_client.py
daraja_api/clients/b2b_api_client.py
daraja_api/clients/b2c_api_client.py
daraja_api/clients/c2b_api_client.py
daraja_api/clients/lnm_api_client.py
daraja_api/clients/reversal_api_client.py